vistrails/__init__.py
vistrails/run.py
vistrails/stop_vistrails_server.py
vistrails/vistrails_server.py
vistrails/api/__init__.py
vistrails/core/__init__.py
vistrails/core/api.py
vistrails/core/application.py
vistrails/core/common.py
vistrails/core/configuration.py
vistrails/core/console_mode.py
vistrails/core/debug.py
vistrails/core/external_connection.py
vistrails/core/inspector.py
vistrails/core/keychain.py
vistrails/core/packagemanager.py
vistrails/core/packagerepository.py
vistrails/core/param_explore.py
vistrails/core/recent_vistrails.py
vistrails/core/reportusage.py
vistrails/core/requirements.py
vistrails/core/startup.py
vistrails/core/theme.py
vistrails/core/thumbnails.py
vistrails/core/upgradeworkflow.py
vistrails/core/analogy/__init__.py
vistrails/core/analogy/eigen.py
vistrails/core/analogy/pipeline_utils.py
vistrails/core/bundles/__init__.py
vistrails/core/bundles/installbundle.py
vistrails/core/bundles/pyimport.py
vistrails/core/cache/__init__.py
vistrails/core/cache/hasher.py
vistrails/core/cache/utils.py
vistrails/core/collection/__init__.py
vistrails/core/collection/entity.py
vistrails/core/collection/mashup.py
vistrails/core/collection/parameter_exploration.py
vistrails/core/collection/schema.sql
vistrails/core/collection/search.py
vistrails/core/collection/test.db
vistrails/core/collection/thumbnail.py
vistrails/core/collection/vistrail.py
vistrails/core/collection/workflow.py
vistrails/core/collection/workflow_exec.py
vistrails/core/data_structures/__init__.py
vistrails/core/data_structures/bijectivedict.py
vistrails/core/data_structures/graph.py
vistrails/core/data_structures/point.py
vistrails/core/data_structures/queue.py
vistrails/core/data_structures/rect.py
vistrails/core/data_structures/stack.py
vistrails/core/db/__init__.py
vistrails/core/db/action.py
vistrails/core/db/io.py
vistrails/core/db/locator.py
vistrails/core/interpreter/__init__.py
vistrails/core/interpreter/base.py
vistrails-2.2.4.dist-info/DESCRIPTION.rst
vistrails-2.2.4.dist-info/METADATA
vistrails-2.2.4.dist-info/RECORD
vistrails-2.2.4.dist-info/WHEEL
vistrails-2.2.4.dist-info/entry_points.txt
vistrails-2.2.4.dist-info/metadata.json
vistrails-2.2.4.dist-info/top_level.txt
