Metadata-Version: 1.1
Name: vistrails
Version: 2.2.4
Summary: Data analysis and visualization tool
Home-page: http://www.vistrails.org/
Author: New York University
Author-email: vistrails-dev@vistrails.org
License: BSD
Keywords: vistrails,provenance,visualization,vtk,nyu,matplotlib
Platform: UNKNOWN
Classifier: Development Status :: 5 - Production/Stable
Classifier: Intended Audience :: Science/Research
Classifier: License :: OSI Approved :: BSD License
Classifier: Programming Language :: Python
Classifier: Programming Language :: Python :: 2.6
Classifier: Programming Language :: Python :: 2.7
Classifier: Programming Language :: Python :: 2 :: Only
Classifier: Topic :: Scientific/Engineering
Classifier: Topic :: Scientific/Engineering :: Information Analysis
Classifier: Topic :: Scientific/Engineering :: Visualization
